hcommit/__init__.py
hcommit/git.py
commitit-0.4.dist-info/METADATA
commitit-0.4.dist-info/WHEEL
commitit-0.4.dist-info/top_level.txt
commitit-0.4.dist-info/RECORD
