Metadata-Version: 2.1
Name: commitit
Version: 0.4
Summary: It is not how good you are, it is about how good people think you are
Author: Didas G. Junior
